mockfs/__init__.py
mockfs/compat.py
mockfs/mfs.py
mockfs/storage.py
mockfs/util.py
mockfs-2.0.2.dist-info/LICENSE
mockfs-2.0.2.dist-info/METADATA
mockfs-2.0.2.dist-info/WHEEL
mockfs-2.0.2.dist-info/top_level.txt
mockfs-2.0.2.dist-info/RECORD
